odoo/addons/crm_lead_dms_category/CHANGELOG.md
odoo/addons/crm_lead_dms_category/README.rst
odoo/addons/crm_lead_dms_category/__init__.py
odoo/addons/crm_lead_dms_category/__manifest__.py
odoo/addons/crm_lead_dms_category/i18n/ca_ES.po
odoo/addons/crm_lead_dms_category/i18n/en_US.po
odoo/addons/crm_lead_dms_category/i18n/es.po
odoo/addons/crm_lead_dms_category/models/__init__.py
odoo/addons/crm_lead_dms_category/models/crm_lead.py
odoo/addons/crm_lead_dms_category/static/description/icon.png
odoo/addons/crm_lead_dms_category/static/description/icon.svg
odoo/addons/crm_lead_dms_category/views/crm_lead_views.xml
odoo_addon_crm_lead_dms_category-16.0.1.0.0.dist-info/METADATA
odoo_addon_crm_lead_dms_category-16.0.1.0.0.dist-info/WHEEL
odoo_addon_crm_lead_dms_category-16.0.1.0.0.dist-info/top_level.txt
odoo_addon_crm_lead_dms_category-16.0.1.0.0.dist-info/RECORD
